mdcatch/__init__.py
mdcatch/config.py
mdcatch/external_job_cryolo.py
mdcatch/external_job_cryolo_train.py
mdcatch/parser.py
mdcatch/run.py
mdcatch/schedule.py
mdcatch/tests/__init__.py
mdcatch/tests/fake_run.py
mdcatch/tests/tests.py
mdcatch/utils/__init__.py
mdcatch/utils/feimrc.py
mdcatch/utils/feixml.py
mdcatch/utils/mdoc.py
mdcatch/utils/misc.py
mdcatch/utils/tiff.py
MDCatch-2.5.dist-info/LICENSE
MDCatch-2.5.dist-info/METADATA
MDCatch-2.5.dist-info/WHEEL
MDCatch-2.5.dist-info/entry_points.txt
MDCatch-2.5.dist-info/top_level.txt
MDCatch-2.5.dist-info/RECORD
